SpatialDE/__init__.py
SpatialDE/aeh.py
SpatialDE/aha.py
SpatialDE/anndata.py
SpatialDE/base.py
SpatialDE/plot.py
SpatialDE/util.py
SpatialDE/scripts/__init__.py
SpatialDE/scripts/spatialde_cli.py
SpatialDE-1.1.3.dist-info/DESCRIPTION.rst
SpatialDE-1.1.3.dist-info/METADATA
SpatialDE-1.1.3.dist-info/RECORD
SpatialDE-1.1.3.dist-info/WHEEL
SpatialDE-1.1.3.dist-info/entry_points.txt
SpatialDE-1.1.3.dist-info/metadata.json
SpatialDE-1.1.3.dist-info/top_level.txt
