Metadata-Version: 2.0
Name: SpatialDE
Version: 1.1.3
Summary: Spatial and Temporal DE test
Home-page: https://github.com/Teichlab/SpatialDE
Author: Valentine Svensson
Author-email: valentine@nxn.se
License: MIT
Platform: UNKNOWN
Requires-Dist: numpy
Requires-Dist: scipy (>=1.0)
Requires-Dist: pandas (>=0.23)
Requires-Dist: tqdm
Requires-Dist: NaiveDE
Requires-Dist: Click
